rockcloner/__init__.py
rockcloner/cli.py
rockcloner/main.py
rockcloner/replicator.py
rockcloner-1.0.1.dist-info/METADATA
rockcloner-1.0.1.dist-info/WHEEL
rockcloner-1.0.1.dist-info/entry_points.txt
rockcloner-1.0.1.dist-info/top_level.txt
rockcloner-1.0.1.dist-info/RECORD
