Metadata-Version: 2.1
Name: rockcloner
Version: 1.0.1
Summary: Discord Server Cloning Tool
Home-page: https://github.com/browished/rock-clonerv1
Author: Devrock
Author-email: audriajou81@gmail.com
Classifier: Programming Language :: Python :: 3
Classifier: License :: OSI Approved :: MIT License
Classifier: Operating System :: OS Independent
Requires-Python: >=3.8
Requires-Dist: discord.py-self>=1.9.0
Requires-Dist: inquirer>=2.10.1
Requires-Dist: colorama>=0.4.4
Requires-Dist: rich>=12.5.1
Requires-Dist: pyfiglet>=0.8.post1
Requires-Dist: aiohttp>=3.8.1
Requires-Dist: psutil>=5.9.0
Requires-Dist: pypresence>=4.2.0
Requires-Dist: questionary>=1.10.0
Requires-Dist: requests>=2.28.1
Requires-Dist: readchar>=3.0.5
